{
  "channel:prom": {
    "meta": {
      "source": "PROMETHEUS_EYE",
      "timestamp": "2025-12-07T23:26:11.091089",
      "market_pressure": -0.6512
    },
    "status": {
      "direction": "WHALE_SELL",
      "flow_multiplier": 0.6
    },
    "details": {
      "BTC/USDT:USDT": -0.732,
      "ETH/USDT:USDT": -0.2782,
      "SOL/USDT:USDT": -0.9435
    }
  },
  "channel:macro": {
    "timestamp": 1765139129.632199,
    "last_update": "23:25:29",
    "macro": {
      "dxy": 98.99,
      "vix": 15.41,
      "nasdaq_chg": 0.31,
      "us10y": 4.14
    },
    "system_mode": {
      "status": "NORMAL",
      "risk_score": -20,
      "reasons": [
        "Dolar Zayıf (Boğa)"
      ]
    }
  },
  "channel:dna": {
    "meta": {
      "source": "OMEGA_JIT",
      "note": "Evren-312384 (Kaos: 2.6)",
      "champion": "084b42",
      "ts": "2025-12-07T23:26:11.771524"
    },
    "strategy": {
      "stop_loss_pct": -0.23,
      "take_profit_pct": 80.8,
      "rsi_buy_level": 5.7,
      "rsi_sell_level": 85.5,
      "position_size_factor": 0.22
    }
  },
  "meta": {
    "source": "GODBRAIN_CHRONICLER_V2",
    "timestamp_utc": "20251207_202611"
  }
}