{
  "channel:prom": {
    "meta": {
      "source": "PROMETHEUS_EYE",
      "timestamp": "2025-12-08T13:30:28.213635",
      "market_pressure": -0.066
    },
    "status": {
      "direction": "NEUTRAL",
      "flow_multiplier": 1.0
    },
    "details": {
      "BTC/USDT:USDT": -0.0449,
      "ETH/USDT:USDT": -0.4609,
      "SOL/USDT:USDT": 0.3077
    }
  },
  "channel:macro": {
    "timestamp": 1765189815.971111,
    "last_update": "13:30:15",
    "macro": {
      "dxy": 98.94,
      "vix": 16.23,
      "nasdaq_chg": 0.31,
      "us10y": 4.14
    },
    "system_mode": {
      "status": "NORMAL",
      "risk_score": -20,
      "reasons": [
        "Dolar Zayıf (Boğa)"
      ]
    }
  },
  "channel:dna": {
    "meta": {
      "source": "OMEGA_JIT",
      "note": "Evren-81619 (Kaos: 2.8)",
      "champion": "d50b48",
      "ts": "2025-12-08T13:30:32.808771"
    },
    "strategy": {
      "stop_loss_pct": -0.27,
      "take_profit_pct": 20.78,
      "rsi_buy_level": 6.3,
      "rsi_sell_level": 87.9,
      "position_size_factor": 0.16
    }
  },
  "meta": {
    "source": "GODBRAIN_CHRONICLER_V2",
    "timestamp_utc": "20251208_103033"
  }
}