{
  "channel:prom": {
    "meta": {
      "source": "PROMETHEUS_EYE",
      "timestamp": "2025-12-07T22:11:26.652193",
      "market_pressure": -0.346
    },
    "status": {
      "direction": "WHALE_SELL",
      "flow_multiplier": 0.6
    },
    "details": {
      "BTC/USDT:USDT": 0.8667,
      "ETH/USDT:USDT": -0.9201,
      "SOL/USDT:USDT": -0.9845
    }
  },
  "channel:macro": {
    "timestamp": 1765134632.7996676,
    "last_update": "22:10:32",
    "macro": {
      "dxy": 98.99,
      "vix": 15.41,
      "nasdaq_chg": 0.31,
      "us10y": 4.14
    },
    "system_mode": {
      "status": "NORMAL",
      "risk_score": -20,
      "reasons": [
        "Dolar Zayıf (Boğa)"
      ]
    }
  },
  "channel:dna": {
    "meta": {
      "source": "OMEGA_JIT",
      "note": "Evren-251526 (Kaos: 4.6)",
      "champion": "efd47e",
      "ts": "2025-12-07T22:11:30.187952"
    },
    "strategy": {
      "stop_loss_pct": -3.68,
      "take_profit_pct": 2.77,
      "rsi_buy_level": 19.5,
      "rsi_sell_level": 91.1,
      "position_size_factor": 0.78
    }
  },
  "meta": {
    "source": "GODBRAIN_CHRONICLER_V2",
    "timestamp_utc": "20251207_191130"
  }
}