{
  "channel:prom": {
    "meta": {
      "source": "PROMETHEUS_EYE",
      "timestamp": "2025-12-08T11:15:44.933981",
      "market_pressure": -0.1772
    },
    "status": {
      "direction": "WHALE_SELL",
      "flow_multiplier": 0.6
    },
    "details": {
      "BTC/USDT:USDT": 0.9791,
      "ETH/USDT:USDT": -0.9968,
      "SOL/USDT:USDT": -0.5141
    }
  },
  "channel:macro": {
    "timestamp": 1765181735.4137478,
    "last_update": "11:15:35",
    "macro": {
      "dxy": 98.88,
      "vix": 15.41,
      "nasdaq_chg": 0.31,
      "us10y": 4.14
    },
    "system_mode": {
      "status": "NORMAL",
      "risk_score": -20,
      "reasons": [
        "Dolar Zayıf (Boğa)"
      ]
    }
  },
  "channel:dna": {
    "meta": {
      "source": "OMEGA_JIT",
      "note": "Evren-890747 (Kaos: 3.6)",
      "champion": "f51884",
      "ts": "2025-12-08T11:15:47.655653"
    },
    "strategy": {
      "stop_loss_pct": -0.1,
      "take_profit_pct": 53.4,
      "rsi_buy_level": 6.4,
      "rsi_sell_level": 83.1,
      "position_size_factor": 0.14
    }
  },
  "meta": {
    "source": "GODBRAIN_CHRONICLER_V2",
    "timestamp_utc": "20251208_081548"
  }
}