{
  "channel:prom": {
    "meta": {
      "source": "PROMETHEUS_EYE",
      "timestamp": "2025-12-08T06:48:09.374740",
      "market_pressure": -0.2392
    },
    "status": {
      "direction": "WHALE_SELL",
      "flow_multiplier": 0.6
    },
    "details": {
      "BTC/USDT:USDT": 0.7484,
      "ETH/USDT:USDT": -0.6312,
      "SOL/USDT:USDT": -0.8346
    }
  },
  "channel:macro": {
    "timestamp": 1765165661.311167,
    "last_update": "06:47:41",
    "macro": {
      "dxy": 98.9,
      "vix": 15.41,
      "nasdaq_chg": 0.31,
      "us10y": 4.14
    },
    "system_mode": {
      "status": "NORMAL",
      "risk_score": -20,
      "reasons": [
        "Dolar Zayıf (Boğa)"
      ]
    }
  },
  "channel:dna": {
    "meta": {
      "source": "OMEGA_JIT",
      "note": "Evren-672960 (Kaos: 3.9)",
      "champion": "da9ef9",
      "ts": "2025-12-08T06:48:11.960212"
    },
    "strategy": {
      "stop_loss_pct": -4.89,
      "take_profit_pct": 18.16,
      "rsi_buy_level": 10.1,
      "rsi_sell_level": 92.4,
      "position_size_factor": 0.4
    }
  },
  "meta": {
    "source": "GODBRAIN_CHRONICLER_V2",
    "timestamp_utc": "20251208_034811"
  }
}