{
  "channel:prom": {
    "meta": {
      "source": "PROMETHEUS_EYE",
      "timestamp": "2025-12-08T09:10:41.812720",
      "market_pressure": -0.2776
    },
    "status": {
      "direction": "WHALE_SELL",
      "flow_multiplier": 0.6
    },
    "details": {
      "BTC/USDT:USDT": -0.253,
      "ETH/USDT:USDT": -0.4835,
      "SOL/USDT:USDT": -0.0963
    }
  },
  "channel:macro": {
    "timestamp": 1765174208.6931057,
    "last_update": "09:10:08",
    "macro": {
      "dxy": 98.89,
      "vix": 15.41,
      "nasdaq_chg": 0.31,
      "us10y": 4.14
    },
    "system_mode": {
      "status": "NORMAL",
      "risk_score": -20,
      "reasons": [
        "Dolar Zayıf (Boğa)"
      ]
    }
  },
  "channel:dna": {
    "meta": {
      "source": "OMEGA_JIT",
      "note": "Evren-789383 (Kaos: 4.6)",
      "champion": "e5f096",
      "ts": "2025-12-08T09:10:44.979734"
    },
    "strategy": {
      "stop_loss_pct": -0.14,
      "take_profit_pct": 40.21,
      "rsi_buy_level": 5.0,
      "rsi_sell_level": 70.5,
      "position_size_factor": 0.21
    }
  },
  "meta": {
    "source": "GODBRAIN_CHRONICLER_V2",
    "timestamp_utc": "20251208_061045"
  }
}