{
  "channel:prom": {
    "meta": {
      "source": "PROMETHEUS_EYE",
      "timestamp": "2025-12-07T22:52:36.283470",
      "market_pressure": 0.0208
    },
    "status": {
      "direction": "NEUTRAL",
      "flow_multiplier": 1.0
    },
    "details": {
      "BTC/USDT:USDT": 0.331,
      "ETH/USDT:USDT": 0.7207,
      "SOL/USDT:USDT": -0.9893
    }
  },
  "channel:macro": {
    "timestamp": 1765137124.3446507,
    "last_update": "22:52:04",
    "macro": {
      "dxy": 98.99,
      "vix": 15.41,
      "nasdaq_chg": 0.31,
      "us10y": 4.14
    },
    "system_mode": {
      "status": "NORMAL",
      "risk_score": -20,
      "reasons": [
        "Dolar Zayıf (Boğa)"
      ]
    }
  },
  "channel:dna": {
    "meta": {
      "source": "OMEGA_JIT",
      "note": "Evren-284990 (Kaos: 2.5)",
      "champion": "785d5c",
      "ts": "2025-12-07T22:52:41.092362"
    },
    "strategy": {
      "stop_loss_pct": -0.45,
      "take_profit_pct": 38.15,
      "rsi_buy_level": 5,
      "rsi_sell_level": 76.7,
      "position_size_factor": 0.13
    }
  },
  "meta": {
    "source": "GODBRAIN_CHRONICLER_V2",
    "timestamp_utc": "20251207_195241"
  }
}