{
  "channel:prom": {
    "meta": {
      "source": "PROMETHEUS_EYE",
      "timestamp": "2025-12-07T21:41:06.091368",
      "market_pressure": -0.3588
    },
    "status": {
      "direction": "WHALE_SELL",
      "flow_multiplier": 0.6
    },
    "details": {
      "BTC/USDT:USDT": -0.2596,
      "ETH/USDT:USDT": 0.1535,
      "SOL/USDT:USDT": -0.9703
    }
  },
  "channel:macro": {
    "timestamp": 1765132809.8104846,
    "last_update": "21:40:09",
    "macro": {
      "dxy": 98.99,
      "vix": 15.41,
      "nasdaq_chg": 0.31,
      "us10y": 4.14
    },
    "system_mode": {
      "status": "NORMAL",
      "risk_score": -20,
      "reasons": [
        "Dolar Zayıf (Boğa)"
      ]
    }
  },
  "channel:dna": {
    "meta": {
      "source": "OMEGA_JIT",
      "note": "Evren-227127 (Kaos: 4.6)",
      "champion": "93a04a",
      "ts": "2025-12-07T21:41:09.233920"
    },
    "strategy": {
      "stop_loss_pct": -1.32,
      "take_profit_pct": 42.41,
      "rsi_buy_level": 6.1,
      "rsi_sell_level": 70.1,
      "position_size_factor": 0.72
    }
  },
  "meta": {
    "source": "GODBRAIN_CHRONICLER_V2",
    "timestamp_utc": "20251207_184109"
  }
}