{
  "channel:prom": {
    "meta": {
      "source": "PROMETHEUS_EYE",
      "timestamp": "2025-12-07T20:19:33.234729",
      "market_pressure": -0.3843
    },
    "status": {
      "direction": "WHALE_SELL",
      "flow_multiplier": 0.6
    },
    "details": {
      "BTC/USDT:USDT": 0.6603,
      "ETH/USDT:USDT": -0.993,
      "SOL/USDT:USDT": -0.8202
    }
  },
  "channel:macro": {
    "timestamp": 1765127951.1684082,
    "last_update": "20:19:11",
    "macro": {
      "dxy": 98.99,
      "vix": 15.41,
      "nasdaq_chg": 0.31,
      "us10y": 4.14
    },
    "system_mode": {
      "status": "NORMAL",
      "risk_score": -20,
      "reasons": [
        "Dolar Zayıf (Boğa)"
      ]
    }
  },
  "channel:dna": {
    "meta": {
      "source": "OMEGA_JIT",
      "note": "Evren-161330 (Kaos: 3.1)",
      "champion": "eb273d",
      "ts": "2025-12-07T20:19:37.462070"
    },
    "strategy": {
      "stop_loss_pct": -0.12,
      "take_profit_pct": 36.17,
      "rsi_buy_level": 5.4,
      "rsi_sell_level": 95,
      "position_size_factor": 0.33
    }
  },
  "meta": {
    "source": "GODBRAIN_CHRONICLER_V2",
    "timestamp_utc": "20251207_171937"
  }
}