{
  "channel:prom": {
    "meta": {
      "source": "PROMETHEUS_EYE",
      "timestamp": "2025-12-08T10:39:56.295812",
      "market_pressure": -0.2015
    },
    "status": {
      "direction": "WHALE_SELL",
      "flow_multiplier": 0.6
    },
    "details": {
      "BTC/USDT:USDT": 0.9944,
      "ETH/USDT:USDT": -0.6922,
      "SOL/USDT:USDT": -0.9068
    }
  },
  "channel:macro": {
    "timestamp": 1765179560.6566796,
    "last_update": "10:39:20",
    "macro": {
      "dxy": 98.89,
      "vix": 15.41,
      "nasdaq_chg": 0.31,
      "us10y": 4.14
    },
    "system_mode": {
      "status": "NORMAL",
      "risk_score": -20,
      "reasons": [
        "Dolar Zayıf (Boğa)"
      ]
    }
  },
  "channel:dna": {
    "meta": {
      "source": "OMEGA_JIT",
      "note": "Evren-862258 (Kaos: 1.0)",
      "champion": "c69c31",
      "ts": "2025-12-08T10:39:57.267018"
    },
    "strategy": {
      "stop_loss_pct": -0.3,
      "take_profit_pct": 126.75,
      "rsi_buy_level": 6.2,
      "rsi_sell_level": 93.5,
      "position_size_factor": 0.47
    }
  },
  "meta": {
    "source": "GODBRAIN_CHRONICLER_V2",
    "timestamp_utc": "20251208_073957"
  }
}